{
  "name": "compact",
  "def": [
    {
      "definition": "Nén",
      "definition_en": "briefly giving the gist of something",
      "pos": "adj"
    }
  ],
  "synonyms": [
    "summary"
  ],
  "antonyms": [
  ],
  "topics": [
    "Information Technology"
  ],
  "targets": [
    "IELTS"
  ],
  "pronunciation": [
    "'kɑmpækt"
  ],
  "frequency": 3.18,
  "audio": "http://www.oxfordlearnersdictionaries.com/media/english/us_pron/c/com/compa/compact__us_1.mp3",
  "image": "http://combiboilersleeds.com/images/compact/compact-8.jpg",
  "example": [
    "A compact style is brief and pithy"
  ]
}